i18n/__init__.py
i18n/__main__.py
i18n/constants.py
i18n/enums.py
i18n/settings.py
i18n/tools.py
i18n/types.py
i18n/utils/__init__.py
i18n/utils/clsutils/__init__.py
i18n/utils/clsutils/generators.py
i18n/utils/gettext/__init__.py
i18n/utils/gettext/contexts.py
i18n/utils/gettext/shortcuts.py
i18n/utils/imputils/__init__.py
i18n/utils/imputils/utils.py
i18n/utils/potfile/__init__.py
i18n/utils/potfile/constants.py
i18n/utils/potfile/potfile.py
i18n/utils/potfile/types.py
translatable_enums-0.0.7.dist-info/LICENSE
translatable_enums-0.0.7.dist-info/METADATA
translatable_enums-0.0.7.dist-info/WHEEL
translatable_enums-0.0.7.dist-info/RECORD
