Metadata-Version: 2.1
Name: translatable-enums
Version: 0.0.7
Summary: Translatable-Enums is a i18n tool which uses built-in Enums as an convenient way to store translation keys.
Home-page: https://github.com/CrazyProger1/Translatable-Enums
License: MIT
Author: CrazyProger1
Author-email: crazyproger1@gmail.com
Requires-Python: >=3.10,<4.0
Classifier: License :: OSI Approved :: MIT License
Classifier: Programming Language :: Python :: 3
Classifier: Programming Language :: Python :: 3.10
Classifier: Programming Language :: Python :: 3.11
Classifier: Programming Language :: Python :: 3.12
Project-URL: Documentation, https://github.com/CrazyProger1/Translatable-Enums
Project-URL: Repository, https://github.com/CrazyProger1/Translatable-Enums
